{
    "title": "Kettlebell Straight Leg Deadlift",
    "description": "A strength exercise.",
    "difficulty": "Beginner",
    "content": [
        {
            "type": "section",
            "title": "Instructions",
            "content": {
                "type": "steps",
                "items": [
                    "Stand with your feet shoulder-width apart and hold a kettlebell in one hand.",
                    "Place the kettlebell on the ground in front of you.",
                    "Bend forward at the hips and grasp the kettlebell with both hands.",
                    "Keep your back straight and your core engaged as you lift the kettlebell off the ground.",
                    "Slowly lower the kettlebell back down to the ground, keeping your back straight and your core engaged.",
                    "Repeat for the desired number of repetitions, then switch hands and repeat on the other side."
                ]
            }
        },
        {
            "type": "section",
            "title": "Benefits",
            "content": {
                "type": "list",
                "items": [
                    "Strengthens the hamstrings, glutes, and lower back muscles",
                    "Improves posture and balance",
                    "Increases grip strength",
                    "Can be modified for different fitness levels",
                    "Engages the core muscles for added stability",
                    "Can be done with minimal equipment",
                    "Helps to prevent lower back injuries"
                ]
            }
        },
        {
            "type": "section",
            "title": "Primary Muscles",
            "content": {
                "type": "list",
                "items": [
                    "Hamstrings",
                    "Glutes",
                    "Lower back",
                    "Core"
                ]
            }
        },
        {
            "type": "section",
            "title": "Variations",
            "content": {
                "type": "list",
                "items": [
                    "Kettlebell Single Leg Deadlift",
                    "Kettlebell Sumo Deadlift",
                    "Kettlebell Romanian Deadlift",
                    "Kettlebell Swing",
                    "Kettlebell Clean"
                ]
            }
        }
    ]
}